[{"@id":"18fcc5c4-97cc-4919-9597-e24b2b9ec5bf","email":"j@gmail.com","transactionTo":"1234 99 95549","name":"James Heui","transactionFrom":"1234 25 98287","amount":7,"message":"(From transfer)"},{"@id":"d3d33ee0-bdbd-49ad-83b6-ee5385c8f833","email":"j@gmail.com","transactionTo":"1234 25 98287","name":"James Heui","transactionFrom":"1234 99 95549","amount":-7,"message":"(From transfer)"},{"@id":"512a9e6f-7d30-4604-9dfa-6c1ae67923af","email":"j@gmail.com","transactionTo":"1234 25 98287","name":"James Heui","transactionFrom":"1234 64 68654","amount":5,"message":"(From transfer)"},{"@id":"72582a63-62c9-4b9c-bb8c-4b55df388e0a","email":"j@gmail.com","transactionTo":"1234 64 68654","name":"James Heui","transactionFrom":"1234 25 98287","amount":-5,"message":"(From transfer)"},{"@id":"d3e47ea4-a69e-42b5-968e-eb7651711ecb","email":"j@gmail.com","transactionTo":"1234 26 59693","name":"jay tay","transactionFrom":"1234 25 98287","amount":-8,"message":"(From payment)"},{"@id":"666169dc-7a20-4483-a451-dbddad1d27bd","email":"ja@gmail.com","transactionTo":"1234 25 98287","name":"James Heui","transactionFrom":"1234 26 59693","amount":8,"message":"(From payment)"},{"@id":"2c17001d-463a-440c-8343-1e230a3e358c","email":"donald@gmail.com","transactionTo":"1234 84 95179","name":"Donald Duck","transactionFrom":"1234 81 77566","amount":10,"message":"(From transfer)"},{"@id":"f024b877-8d92-4a08-835a-8e655a4d5864","email":"donald@gmail.com","transactionTo":"1234 81 77566","name":"Donald Duck","transactionFrom":"1234 84 95179","amount":-10,"message":"(From transfer)"},{"@id":"17edef4d-b86f-492e-8af0-703515ee9fcb","email":"donald@gmail.com","transactionTo":"1234 26 59693","name":"jay tay","transactionFrom":"1234 84 95179","amount":-40,"message":"(From payment)"},{"@id":"0373e698-e510-46ab-9baf-e3a256e65978","email":"ja@gmail.com","transactionTo":"1234 84 95179","name":"Donald Duck","transactionFrom":"1234 26 59693","amount":40,"message":"(From payment)"},{"@id":"0bafff8b-b465-40fb-8d36-d41573a94cbf","email":"donald@gmail.com","transactionTo":"1234 81 77566","name":"Donald Duck","transactionFrom":"1234 51 64962","amount":7,"message":"(From transfer)"},{"@id":"7af1396e-4224-4293-b804-e017c09ff9bd","email":"donald@gmail.com","transactionTo":"1234 51 64962","name":"Donald Duck","transactionFrom":"1234 81 77566","amount":-7,"message":"(From transfer)"},{"@id":"4c130e4e-25e7-4df2-aac5-bc8ed513d04f","email":"donald@gmail.com","transactionTo":"1234 84 95179","name":"Donald Duck","transactionFrom":"1234 51 64962","amount":2,"message":"(From transfer)"},{"@id":"609a348c-c0f1-47d9-a8d3-f72a574b609a","email":"donald@gmail.com","transactionTo":"1234 51 64962","name":"Donald Duck","transactionFrom":"1234 84 95179","amount":-2,"message":"(From transfer)"},{"@id":"b7f02cc7-bdf1-4c72-a6fc-537ecd395313","email":"donald@gmail.com","transactionTo":"1234 84 95179","name":"Donald Duck","transactionFrom":"1234 51 64962","amount":3,"message":"(From transfer)"},{"@id":"a9e59842-0059-42a1-b5ea-13d3486b2837","email":"donald@gmail.com","transactionTo":"1234 51 64962","name":"Donald Duck","transactionFrom":"1234 84 95179","amount":-3,"message":"(From transfer)"},{"@id":"eb290a9a-f1d0-4ed0-86da-3479bceaebc6","email":"donald@gmail.com","transactionTo":"1234 84 95179","name":"Donald Duck","transactionFrom":"1234 51 64962","amount":7,"message":"(From transfer)"},{"@id":"c7b984fe-6456-4472-a594-edfc4f7b9717","email":"donald@gmail.com","transactionTo":"1234 51 64962","name":"Donald Duck","transactionFrom":"1234 84 95179","amount":-7,"message":"(From transfer)"},{"@id":"bfc9b3a0-bd7a-4e86-9920-7e5ea12f0884","email":"donald@gmail.com","transactionTo":"1234 26 59693","name":"jay tay","transactionFrom":"1234 84 95179","amount":-3,"message":"(From payment)"},{"@id":"a59416dd-8ff4-488e-89a6-1948c9d9d84b","email":"ja@gmail.com","transactionTo":"1234 84 95179","name":"Donald Duck","transactionFrom":"1234 26 59693","amount":3,"message":"(From payment)"}]